README.md
setup.cfg
setup.py
dbug12/__init__.py
dbug12/cli.py
dbug12/debugger.py
dbug12.egg-info/PKG-INFO
dbug12.egg-info/SOURCES.txt
dbug12.egg-info/dependency_links.txt
dbug12.egg-info/entry_points.txt
dbug12.egg-info/requires.txt
dbug12.egg-info/top_level.txt