Metadata-Version: 2.1
Name: dbug12
Version: 0.2.0
Summary: Python API for D-Bug12 compatible boards
Home-page: https://github.com/mlndz28/d-bug12
Author: Fabian Melendez
Author-email: fabian.melendez.a@gmail.com
License: UNKNOWN
Download-URL: https://github.com/mlndz28/d-bug12/archive/v0.2.0.tar.gz
Keywords: D-Bug12,HCS12,Dragon12,cli,api
Platform: UNKNOWN
Classifier: Programming Language :: Python :: 2
Classifier: Programming Language :: Python :: 3
Classifier: License :: OSI Approved :: MIT License
Classifier: Operating System :: POSIX :: Linux
Classifier: Operating System :: Microsoft :: Windows
